rowbot/__init__.py
rowbot/bootstrap.py
rowbot/cli.py
rowbot/configs/__init__.py
rowbot/configs/cmds_unix.json
rowbot/configs/cmds_win.json
rowbot/configs/data.py
rowbot/controllers/__init__.py
rowbot/controllers/menu.py
rowbot/models/__init__.py
rowbot/models/entry.py
rowbot/services/__init__.py
rowbot/services/commands.py
rowbot/services/storage.py
rowbot/views/__init__.py
rowbot/views/static.py
rowbot-0.1.0.dist-info/licenses/LICENSE
rowbot-0.1.0.dist-info/METADATA
rowbot-0.1.0.dist-info/WHEEL
rowbot-0.1.0.dist-info/entry_points.txt
rowbot-0.1.0.dist-info/top_level.txt
rowbot-0.1.0.dist-info/RECORD
