Metadata-Version: 2.4
Name: rowbot
Version: 0.1.0
Summary: Interactive tool to simplify commands management in a shell.
Author-email: Santiago La Corte <selacorte@uc.cl>
License: MIT License
Project-URL: homepage, https://gitlab.com/slacorte/rowbot
Project-URL: documentation, https://gitlab.com/slacorte/rowbot-/tree/main/README.md
Project-URL: issues, https://gitlab.com/slacorte/rowbot-/issues
Project-URL: changelog, https://gitlab.com/slacorte/rowbot-/tree/main/CHANGELOG.md
Project-URL: download, https://gitlab.com/slacorte/rowbot-/releases
Classifier: Environment :: Console
Classifier: Intended Audience :: Developers
Classifier: License :: OSI Approved :: MIT License
Classifier: Natural Language :: English
Classifier: Operating System :: OS Independent
Classifier: Programming Language :: Python
Classifier: Topic :: Software Development :: Libraries :: Application Frameworks
Classifier: Topic :: Software Development :: Libraries :: Python Modules
Requires-Python: <4.0,>=3.10
License-File: LICENSE
Requires-Dist: click<9.0,>=8.1
Requires-Dist: dependency-injector<5.0,>=4.4.0
Requires-Dist: pydantic<3.0,>=2.1
Requires-Dist: pydantic-settings<3.0,>=2.8
Requires-Dist: windows-curses; sys_platform == "win32"
Provides-Extra: build
Requires-Dist: build==1.2.2.post1; extra == "build"
Requires-Dist: python-semantic-release==9.21.0; extra == "build"
Requires-Dist: setuptools>=70.0.0; extra == "build"
Requires-Dist: twine==6.1.0; extra == "build"
Requires-Dist: wheel==0.45.1; extra == "build"
Provides-Extra: dev
Requires-Dist: bandit==1.8.3; extra == "dev"
Requires-Dist: black==24.8.0; extra == "dev"
Requires-Dist: commitizen==4.4.1; extra == "dev"
Requires-Dist: isort==5.13.2; extra == "dev"
Requires-Dist: pre-commit==4.1.0; extra == "dev"
Requires-Dist: pydocstyle==6.3.0; extra == "dev"
Requires-Dist: pylint==3.2.6; extra == "dev"
Provides-Extra: test
Requires-Dist: pytest==8.3.2; extra == "test"
Requires-Dist: pytest-cov==5.0.0; extra == "test"
Dynamic: license-file
